spatial_graph/__init__.py
spatial_graph/_dtypes.py
spatial_graph/_spatial_graph.py
spatial_graph/_util.py
spatial_graph/_graph/__init__.py
spatial_graph/_graph/graph.py
spatial_graph/_graph/graph_base.py
spatial_graph/_graph/views.py
spatial_graph/_graph/wrapper_template.pyx
spatial_graph/_graph/src/LICENSE.txt
spatial_graph/_graph/src/graph_lite.h
spatial_graph/_rtree/__init__.py
spatial_graph/_rtree/line_rtree.py
spatial_graph/_rtree/point_rtree.py
spatial_graph/_rtree/rtree.py
spatial_graph/_rtree/tree_base.py
spatial_graph/_rtree/wrapper_template.pyx
spatial_graph/_rtree/src/ARCHITECTURE.md
spatial_graph/_rtree/src/LICENSE
spatial_graph/_rtree/src/config.h
spatial_graph/_rtree/src/rtree.c
spatial_graph/_rtree/src/rtree.h
spatial_graph-0.0.4.dist-info/METADATA
spatial_graph-0.0.4.dist-info/WHEEL
spatial_graph-0.0.4.dist-info/licenses/LICENSE
spatial_graph-0.0.4.dist-info/RECORD
