Metadata-Version: 2.4
Name: spatial-graph
Version: 0.0.4
Summary: A spatial graph datastructure for python.
Project-URL: homepage, https://github.com/funkelab/spatial_graph
Project-URL: repository, https://github.com/funkelab/spatial_graph
Author-email: Jan Funke <funkej@janelia.hhmi.org>, Talley Lambert <talley.lambert@gmail.com>
License: MIT
License-File: LICENSE
Classifier: Development Status :: 3 - Alpha
Classifier: Intended Audience :: Developers
Classifier: License :: OSI Approved :: MIT License
Classifier: Programming Language :: Python :: 3.9
Classifier: Programming Language :: Python :: 3.10
Classifier: Programming Language :: Python :: 3.11
Classifier: Programming Language :: Python :: 3.12
Classifier: Programming Language :: Python :: 3.13
Classifier: Typing :: Typed
Requires-Python: >=3.9
Requires-Dist: ct3>=3.3.3
Requires-Dist: numpy
Requires-Dist: setuptools>=75.8.0
Requires-Dist: witty>=v0.3.0
